pyzpaqlib/__init__.py
pyzpaqlib/zpaqlib.py
pyzpaqlib/bin/zpaq.exe
pyzpaqlib/bin/zpaq64.exe
pyzpaqlib-0.1.0.dist-info/METADATA
pyzpaqlib-0.1.0.dist-info/WHEEL
pyzpaqlib-0.1.0.dist-info/top_level.txt
pyzpaqlib-0.1.0.dist-info/RECORD
